MANIFEST.in
README
requirements.txt
setup.py
ajenti.plugin.traffic.egg-info/PKG-INFO
ajenti.plugin.traffic.egg-info/SOURCES.txt
ajenti.plugin.traffic.egg-info/dependency_links.txt
ajenti.plugin.traffic.egg-info/requires.txt
ajenti.plugin.traffic.egg-info/top_level.txt
ajenti_plugin_traffic/README.md
ajenti_plugin_traffic/__init__.py
ajenti_plugin_traffic/plugin.yml
ajenti_plugin_traffic/requirements.txt
ajenti_plugin_traffic/views.py
ajenti_plugin_traffic/widget.py
ajenti_plugin_traffic/locale/app.pot
ajenti_plugin_traffic/locale/af/LC_MESSAGES/app.js
ajenti_plugin_traffic/locale/af/LC_MESSAGES/app.po
ajenti_plugin_traffic/locale/ar/LC_MESSAGES/app.js
ajenti_plugin_traffic/locale/ar/LC_MESSAGES/app.po
ajenti_plugin_traffic/locale/be/LC_MESSAGES/app.js
ajenti_plugin_traffic/locale/be/LC_MESSAGES/app.po
ajenti_plugin_traffic/locale/bg/LC_MESSAGES/app.js
ajenti_plugin_traffic/locale/bg/LC_MESSAGES/app.po
ajenti_plugin_traffic/locale/bn/LC_MESSAGES/app.js
ajenti_plugin_traffic/locale/bn/LC_MESSAGES/app.po
ajenti_plugin_traffic/locale/bs/LC_MESSAGES/app.js
ajenti_plugin_traffic/locale/bs/LC_MESSAGES/app.po
ajenti_plugin_traffic/locale/ca/LC_MESSAGES/app.js
ajenti_plugin_traffic/locale/ca/LC_MESSAGES/app.po
ajenti_plugin_traffic/locale/cs/LC_MESSAGES/app.js
ajenti_plugin_traffic/locale/cs/LC_MESSAGES/app.po
ajenti_plugin_traffic/locale/da/LC_MESSAGES/app.js
ajenti_plugin_traffic/locale/da/LC_MESSAGES/app.po
ajenti_plugin_traffic/locale/de/LC_MESSAGES/app.js
ajenti_plugin_traffic/locale/de/LC_MESSAGES/app.po
ajenti_plugin_traffic/locale/el/LC_MESSAGES/app.js
ajenti_plugin_traffic/locale/el/LC_MESSAGES/app.po
ajenti_plugin_traffic/locale/en/LC_MESSAGES/app.po
ajenti_plugin_traffic/locale/eo/LC_MESSAGES/app.js
ajenti_plugin_traffic/locale/eo/LC_MESSAGES/app.po
ajenti_plugin_traffic/locale/es-ES/LC_MESSAGES/app.js
ajenti_plugin_traffic/locale/es-ES/LC_MESSAGES/app.po
ajenti_plugin_traffic/locale/et/LC_MESSAGES/app.js
ajenti_plugin_traffic/locale/et/LC_MESSAGES/app.po
ajenti_plugin_traffic/locale/fa/LC_MESSAGES/app.js
ajenti_plugin_traffic/locale/fa/LC_MESSAGES/app.po
ajenti_plugin_traffic/locale/fi/LC_MESSAGES/app.js
ajenti_plugin_traffic/locale/fi/LC_MESSAGES/app.po
