Metadata-Version: 1.2
Name: ajenti.plugin.traffic
Version: 0.17
Summary: Traffic Widget
Home-page: https://ajenti.org
Author: Ajenti project
Author-email: e@ajenti.org
License: UNKNOWN
Platform: UNKNOWN
Requires-Python: >=3
